tasknotify/__init__.py
tasknotify/config.json
tasknotify/main.py
task_notify-0.8.3.dist-info/LICENSE.txt
task_notify-0.8.3.dist-info/METADATA
task_notify-0.8.3.dist-info/WHEEL
task_notify-0.8.3.dist-info/entry_points.txt
task_notify-0.8.3.dist-info/top_level.txt
task_notify-0.8.3.dist-info/RECORD
