Metadata-Version: 2.1
Name: task-notify
Version: 0.8.3
Summary: Run tasks and send notifications if they fail.
Author: Christoph Stein
License: MIT
Project-URL: homepage, https://gitlab.com/s7one/task-notify
Project-URL: documentation, https://gitlab.com/s7one/task-notify
Project-URL: repository, https://gitlab.com/s7one/task-notify
Keywords: Tasks,Email,Notifications
Classifier: Programming Language :: Python :: 3
Classifier: Development Status :: 4 - Beta
Classifier: Environment :: Console
Requires-Python: >=3.9
License-File: LICENSE.txt
